operacionestest/__init__.py
operacionestest/modulo.py
operacionestest-0.1.1.dist-info/METADATA
operacionestest-0.1.1.dist-info/WHEEL
operacionestest-0.1.1.dist-info/top_level.txt
operacionestest-0.1.1.dist-info/RECORD
