Metadata-Version: 2.4
Name: operacionestest
Version: 0.1.1
Summary: libreria de operaciones básicas
Author: Alexis Ruales
License: MIT
Requires-Python: >=3.12.4
Dynamic: author
Dynamic: description
Dynamic: description-content-type
Dynamic: license
Dynamic: requires-python
Dynamic: summary
